{
  "slug": "the-riddles-of-king-heithrek",
  "key": "TheRiddlesOfKingHeithrek",
  "title": {
    "on": "Heiðreksgátur",
    "ru": "Загадки Хейдрека (Загадки Гестумблинди)",
    "en": "The riddles of King Heithrek"
  },
  "description": {
    "on": "",
    "ru": "Одного человека звали Гестумблинди, могучего и великого недруга конунга Хейдрека. Конунг послал ему сообщение, чтобы он пришел на встречу с ним для примирения, если он хочет спасти свою жизнь.",
    "en": "Gestumblindi said: \"That would I have which I had yesterday; heed what I had: men’s hamperer, word’s hinderer, and speeder of speech. Aright read now this riddle, Heithrek!\" Heithrek said: \"Good is thy riddle, Gestumblindi, and guessed it is: give him ale! That hampers many a man’s wits; by it, some become talkative, but other men’s wits are mazed.\""
  },
  "source": {
    "on": "",
    "ru": "Древнеисландский текст, ред. Guðni Jónsson. Текст на русском языке в переводе Т. В. Топоровой",
    "en": "An ancient Icelandic text, edited by Guðni Jónsson.\nTranslation by Lee M. Hollander (1936)."
  },
  "texts": {
    "on": [
      {
        "id": "1",
        "type": "prose",
        "number": "",
        "lines": [
          "Gestumblindi hét einn ríkr maðr í Reiðgotalandi. Hann var í óblíðu Heiðreks konungs. Í konungs hirð váru þeir sjau menn, er dæma skyldu öll mál manna þar í landi. Heiðrekr konungr blótaði Frey. Þann gölt, er mestan fekk, skyldi hann gefa Frey. Kölluðu þeir hann svá helgan, at yfir hans burst skyldi sverja um öll stór mál, ok skyldi þeim gelti blóta at sónarblóti. Jólaftan skyldi leiða sónargöltinn í höll fyrir konung, ok lögðu menn þá hendr yfir burst hans ok strengja heit. Heiðrekr konungr strengði þess heit, at engi maðr skyldi svá mikit hafa af gert við hann, ef á vald hans kæmi, at eigi skyldi kost eiga at hafa dóm spekinga hans. Sá skyldi ok friðheilagr vera fyrir honum, ef hann bæri upp gátur þær, er konungr kynni eigi ór at leysa. En er menn freistuðu at bera upp gátur fyrir honum, þá varð engi sú upp borin, er hann réði eigi.",
          "Konungr sendi orð Gestumblinda, at hann kæmi til hans, ok setti honum dag, ella sagðist konungr mundu láta koma til hans. Honum þótti hvárgi góðr kostrinn, því at hann vissi sik vanfæran at skipta orðum við konung. Honum þótti ok sín ván eigi góð, ef hann yrði at hafa dóm spekinganna, því at sakir váru nógar. Veit hann ok, ef konungs menn koma til hans, at þat kostar líf hans. Síðan blótaði hann Óðin ok bað hann fulltings ok hét honum stórum gjöfum.",
          "Eitt kveld kom gestr til Gestumblinda. Hann nefndist Gestumblindi. Þeir váru svá líkir, at hvárgan kenndi fyrir annan. Þeir skiptu klæðum, ok fór bóndi at hirða sik, en allir hugðu þar vera bónda, er gestrinn var. Þessi maðr ferr á konungs fund ok heilsar honum.",
          "Konungr sá við honum ok þagði.",
          "Gestumblindi mælti: \"Því em ek hér kominn, herra, at ek vil sættast við yðr.\"",
          "Konungr spurði: \"Viltu hafa dóm spekinga?\"",
          "Gestumblindi mælti: \"Eru engar fleiri undanlausnir?\"",
          "Konungr segir: \"Bera máttu upp gátur. Skaltu lauss, ef ek sé eigi.\"",
          "Gestumblindi svarar: \"Lítt em ek þar til færr, en harðr er á annat borð.\"",
          "Konungr mælti: \"Viltu heldr dóminn?\"",
          "Nei segir hann, heldr vil ek bera gáturnar upp.",
          "Konungr mælti: \"Þat er ok rétt, en mikit liggr á. Sigrar þú mik, þá skaltu eiga dóttur mína, ok á þér eigi þess at varna. En ólíkr ertu til mikillar speki, en aldri varð þat enn, at ek sá eigi gátur þær, er fyrir mik váru upp bornar.",
          "Var síðan stóll settr undir Gestumblinda, ok hugðu menn gott til at heyra þar vitrlig orð.\"",
          "Þá mælti Gestumblindi:"
        ],
        "placeholder": false
      },
      {
        "id": "2",
        "type": "stanza",
        "number": "1.",
        "lines": [
          "\"Hafa ek þat vilda,",
          "er ek hafða í gær,",
          "vittu, hvat þat var:",
          "lýða lemill,",
          "orða tefill",
          "ok orða upphefill.",
          "Heiðrekr konungr,",
          "hygg þú at gátu.",
          "Góð er gáta þín,",
          "Gestumblindi,",
          "getit er þeirar:\""
        ],
        "placeholder": false
      },
      {
        "id": "3",
        "type": "prose",
        "number": "",
        "lines": [
          "Fái honum mungát. Þat lemr margra manna vit. Sumir verða margmæltir þar af, en sumum vefst tungubragð.",
          "Gestumblindi mælti:"
        ],
        "placeholder": false
      },
      {
        "id": "4",
        "type": "stanza",
        "number": "2.",
        "lines": [
          "\"Heiman ek fór,",
          "heiman ek för gerðak,",
          "sá ek á veg vega,",
          "vegr var undir",
          "ok vegr yfir",
          "ok vegr á alla vega.",
          "Heiðrekr konungr,",
          "hygg þú at gátu.",
          "Góð er gáta þín,",
          "Gestumblindi,",
          "getit er þeirar:\""
        ],
        "placeholder": false
      },
      {
        "id": "5",
        "type": "prose",
        "number": "",
        "lines": [
          "Þar fórtu yfir brú, ok var árvegrinn undir henni, en fuglar flugu yfir höfði þér ok tveim megin þín; þat var þeira vegr; þú sátt lax í ánni, ok var þat hans vegr.",
          "Gestumblindi mælti:"
        ],
        "placeholder": false
      },
      {
        "id": "6",
        "type": "stanza",
        "number": "3.",
        "lines": [
          "\"Hvat er þat drykkja,",
          "er ek drakk í gær,",
          "var-at þat vín né vatn,",
          "mjöðr né mungát",
          "né matar ekki,",
          "þó gekk ek þorstalauss þaðan?",
          "Heiðrekr konungr,",
          "hygg þú at gátu?",
          "Góð er gáta þín,",
          "Gestumblindi,",
          "getit er þeirar:\""
        ],
        "placeholder": false
      },
      {
        "id": "7",
        "type": "prose",
        "number": "",
        "lines": [
          "Þar lagðist þú í forsælu ok kældir varir þínar á dögg. En ef þú ert sá Gestumblindi, sem ek ætlaða, þá ertu vitrari en ek hugða, því at ek hefi spurt orð þín óvitrlig, en gerast nú á leið spaklig.",
          "Þat er ván, at mik þrjóti brátt, segir Gestumblindi, en þó vilda ek enn, at þér hlýddið:"
        ],
        "placeholder": false
      },
      {
        "id": "8",
        "type": "stanza",
        "number": "4.",
        "lines": [
          "\"Hverr er sá inn hvelli,",
          "er gengr harðar götur",
          "ok hefir hann þær fyrr of farit,",
          "mjök fast kyssir",
          "ok hefir munna tvá",
          "ok á gulli einu gengr?",
          "Heiðrekr konungr,",
          "hygg þú at gátu.",
          "Góð er gáta þín,",
          "Gestumblindi,",
          "getit er þeirar:\""
        ],
        "placeholder": false
      },
      {
        "id": "9",
        "type": "prose",
        "number": "",
        "lines": [
          "Þat er gullsmiðs hamarr, sem gull er með slegit. Hann kveðr hátt við, er hann á harðan steðja, ok þat er hans gata.",
          "Gestumblindi mælti:"
        ],
        "placeholder": false
      },
      {
        "id": "10",
        "type": "stanza",
        "number": "5.",
        "lines": [
          "\"Hverr er sá inn mikli,",
          "er ferr mold yfir,",
          "svelgr hann vötn ok veisur,",
          "glygg hann óask,",
          "en guma eigi",
          "ok yrkir á sól til saka?",
          "Heiðrekr konungr,",
          "hygg þú at gátu.",
          "Góð er gáta þín,",
          "Gestumblindi,",
          "getit er þeirar:\""
        ],
        "placeholder": false
      },
      {
        "id": "11",
        "type": "prose",
        "number": "",
        "lines": [
          "Þat er myrkvi. Fyrir honum sér eigi sól, en hann hverfr þegar, er vindr kemr, ok megu menn ekki at honum gera; hann drepr skini sólar. En vélasamliga berr þú upp slíkar gátur ok vanmæli, hverr sem þú ert.",
          "Gestumblindi mælti:"
        ],
        "placeholder": false
      },
      {
        "id": "12",
        "type": "stanza",
        "number": "6.",
        "lines": [
          "\"Hverr er sá inn mikli,",
          "er mörgu ræðr",
          "ok horfir til heljar hálfr,",
          "öldum bergr,",
          "en við jörð sakask,",
          "ef hann hefir sér vel traustan vin?",
          "Heiðrekr konungr,",
          "hygg þú at gátu.",
          "Góð er gáta þín,",
          "Gestumblindi,",
          "getit er þeirar:\""
        ],
        "placeholder": false
      },
      {
        "id": "13",
        "type": "prose",
        "number": "",
        "lines": [
          "Þat er akkeri með digrum ok sterkum streng. Þat ræðr mörgu skipi. Þat hrífr öðrum fleini í jörð, ok horfir sá til heljar; hann bergr mörgum manni. En mjök undrast ek orðfimi þína ok vitrleik.",
          "Gestumblindi mælti: \"Ek em nú ok náliga þrotinn at gátum, en frekr er hverr til fjörsins.\""
        ],
        "placeholder": false
      },
      {
        "id": "14",
        "type": "stanza",
        "number": "7.",
        "lines": [
          "\"Hverr byggir há fjöll,",
          "hverr fellr í djúpa dali,",
          "hverr andalauss lifir,",
          "hverr æva þegir?",
          "Heiðrekr konungr,",
          "hygg þú at gátu.",
          "Góð er gáta þín,",
          "Gestumblindi,",
          "getit er þeirar:\""
        ],
        "placeholder": false
      },
      {
        "id": "15",
        "type": "prose",
        "number": "",
        "lines": [
          "Hrafn byggir jafnan á hám fjöllum, en dögg fellr jafnan í djúpa dali, fiskr lifir andalauss, en þjótandi foss þegir aldrigi.",
          "Vandast mun nú, segir Gestumblindi, ok veitk-a ek nú, hvat fyrir verðr."
        ],
        "placeholder": false
      },
      {
        "id": "16",
        "type": "stanza",
        "number": "8.",
        "lines": [
          "\"Hvat er þat undra,",
          "er ek úti sá",
          "fyrir Dellings durum;",
          "höfði sínu",
          "vísar heljar til,",
          "en fótum til sólar snýr?",
          "Heiðrekr konungr,",
          "hygg þú at gátu.",
          "Góð er gáta þín,",
          "Gestumblindi,",
          "getit er þeirar:\""
        ],
        "placeholder": false
      },
      {
        "id": "17",
        "type": "prose",
        "number": "",
        "lines": [
          "Þat er laukr. Höfuð hans horfir í jörð, en blöðin í loft.",
          "Gestumblindi mælti:"
        ],
        "placeholder": false
      },
      {
        "id": "18",
        "type": "stanza",
        "number": "9.",
        "lines": [
          "\"Hvat er þat undra,",
          "er ek úti sá",
          "fyrir Dellings durum:",
          "ókyrrir tveir",
          "andalausir",
          "sára lauk suðu?",
          "Heiðrekr konungr,",
          "hygg þú at gátu.",
          "Góð er gáta þín,",
          "Gestumblindi,",
          "getit er þeirar:\""
        ],
        "placeholder": false
      },
      {
        "id": "19",
        "type": "prose",
        "number": "",
        "lines": [
          "Smiðbelgir eru þat. Þeir hafa vind, en engan anda.",
          "Gestumblindi mælti:"
        ],
        "placeholder": false
      },
      {
        "id": "20",
        "type": "stanza",
        "number": "10.",
        "lines": [
          "\"Hvat er þat undra,",
          "er ek úti sá",
          "fyrir Dellings durum:",
          "hvítir fljúgendr",
          "hellu ljósta,",
          "en svartir í sand grafask?",
          "Heiðrekr konungr,",
          "hygg þú at gátu.",
          "Góð er gáta þín,",
          "Gestumblindi,",
          "getit er þeirar:\""
        ],
        "placeholder": false
      },
      {
        "id": "21",
        "type": "prose",
        "number": "",
        "lines": [
          "Smækkast nú gáturnar, en þat er hagl ok regn, því at hagli lýstr á stræti, en regns dropar sökkva í sand ok sækja í jörð.",
          "Gestumblindi mælti:"
        ],
        "placeholder": false
      },
      {
        "id": "22",
        "type": "stanza",
        "number": "11.",
        "lines": [
          "\"Hvat er þat undra,",
          "er ek úti sá",
          "fyrir Dellings durum:",
          "svartan gölt",
          "ek sá í sauri vaða,",
          "ok reis-at honum burst á baki?",
          "Heiðrekr konungr,",
          "hygg þú at gátu.",
          "Góð er gáta þín,",
          "Gestumblindi,",
          "getit er þeirar:\""
        ],
        "placeholder": false
      },
      {
        "id": "23",
        "type": "prose",
        "number": "",
        "lines": [
          "Þat er tordýfill, ok er nú margt til tínt, er tordýflar eru ríkra manna spurningar.",
          "Gestumblindi svarar: \"Frest eru böls bezt, en margr maðr vill at meira leita, ok sést því sumum yfir. Sé ek nú ok, at allra útfæra verðr at leita.\""
        ],
        "placeholder": false
      },
      {
        "id": "24",
        "type": "stanza",
        "number": "12.",
        "lines": [
          "\"Hvat er þat undra,",
          "er ek úti sá",
          "fyrir Dellings durum:",
          "tíu hefr tungur,",
          "tuttugu augu,",
          "fjóra tigu fóta,",
          "ferr hart sú vættr?",
          "Heiðrekr konungr,",
          "hygg þú at gátu.",
          "Góð er gáta þín,",
          "Gestumblindi,",
          "getit er þeirar:\""
        ],
        "placeholder": false
      },
      {
        "id": "25",
        "type": "prose",
        "number": "",
        "lines": [
          "Þar sáttu sú, ok váru í henni níu grísir. Lét þá konungr drepa súna, ok váru í henni níu grísir, sem Gestumblindi hafði sagt.",
          "Þá mælti konungr: \"Eigi veit ek nú, nema vitrir eigi nú hlut í, ok eigi veit ek, hvat manna þú ert.\"",
          "Gestumblindi svarar: \"Slíkr em ek sem þú mátt sjá, ok vilda ek gjarnan þiggja líf mitt ok vera lauss af þessum þrautum.\"",
          "Konungr svarar: \"Upp skaltu bera gátur, þar til er þik þrýtr ella mik at ráða.\"",
          "Gestumblindi mælti:"
        ],
        "placeholder": false
      },
      {
        "id": "26",
        "type": "stanza",
        "number": "13.",
        "lines": [
          "\"Hvat er þat undra,",
          "er ek úti sá",
          "fyrir Dellings durum:",
          "ofarliga flýgr,",
          "almhljóð gellr,",
          "harðar eru, hilmir?",
          "Heiðrekr konungr,",
          "hygg þú at gátu.",
          "Góð er gáta þín,",
          "Gestumblindi,",
          "getit er þeirar:\""
        ],
        "placeholder": false
      },
      {
        "id": "27",
        "type": "prose",
        "number": "",
        "lines": [
          "\"Ör er þat,\" segir konungr.",
          "Gestumblindi mælti:"
        ],
        "placeholder": false
      },
      {
        "id": "28",
        "type": "stanza",
        "number": "14.",
        "lines": [
          "\"Hvat er þat undra,",
          "er ek úti sá",
          "fyrir Dellings durum:",
          "fætr hefir átta,",
          "en fjögur augu,",
          "berr þat ofar kné en kvið?",
          "Heiðrekr konungr,",
          "hygg þú at gátu.\""
        ],
        "placeholder": false
      },
      {
        "id": "29",
        "type": "prose",
        "number": "",
        "lines": [
          "Konungr mælti: \"Er nú bæði, at þú hefir hattin síðan, enda sér þú niðr undan fleira en flestir menn aðrir, er þú hugsar hvert skrípi jarðarinnar. En þat er köngurváfa.\"",
          "Gestumblindi mælti:"
        ],
        "placeholder": false
      },
      {
        "id": "30",
        "type": "stanza",
        "number": "15.",
        "lines": [
          "\"Hvat er þat undra,",
          "er ek úti sá",
          "fyrir Dellings durum:",
          "lýðum lýsir,",
          "en logi gleypir,",
          "ok keppask um þat vargar ávallt?",
          "Heiðrekr konungr,",
          "hygg þú at gátu.",
          "Góð er gáta þín,",
          "Gestumblindi,",
          "getit er þeirar:\""
        ],
        "placeholder": false
      },
      {
        "id": "31",
        "type": "prose",
        "number": "",
        "lines": [
          "Þat er sól. Hon lýsir lönd öll ok skínn yfir alla menn, en Skalli ok Hatti heita vargar, þat eru úlfar, en annarr þeira ferr fyrir, en annarr eftir sólu.",
          "Gestumblindi mælti:"
        ],
        "placeholder": false
      },
      {
        "id": "32",
        "type": "stanza",
        "number": "16.",
        "lines": [
          "\"Hvat er þat undra,",
          "er ek úti sá",
          "fyrir Dellings durum:",
          "horni harðara,",
          "hrafni svartara,",
          "skafti réttara,",
          "skjalli hvítara?",
          "Heiðrekr konungr,",
          "hygg þú at gátu.",
          "Góð er gáta þín,",
          "Gestumblindi,",
          "getit er þeirar:\""
        ],
        "placeholder": false
      },
      {
        "id": "33",
        "type": "prose",
        "number": "",
        "lines": [
          "Þú sátt hrafntinnu, ok skein á sólar geisli, er lá í einu húsi. Eða kanntu ekki á annan veg gátur upp at bera en hafa it sama upphaf at, þar sem mér virðist þú fróðr maðr?",
          "Þá mælti Gestumblindi:"
        ],
        "placeholder": false
      },
      {
        "id": "34",
        "type": "stanza",
        "number": "17.",
        "lines": [
          "\"Báru brúðir",
          "bleikhaddaðar,",
          "ambáttir tvær,",
          "öl til skemmu;",
          "var-a þat höndum horfit",
          "né hamri klappat;",
          "þó er fyrir eyjar útan",
          "örðigr, sá er ker gerði.",
          "Heiðrekr konungr,",
          "hygg þú at gátu.",
          "Góð er gáta þín,",
          "Gestumblindi,",
          "getit er þeirar:\""
        ],
        "placeholder": false
      },
      {
        "id": "35",
        "type": "prose",
        "number": "",
        "lines": [
          "Þat eru æðar tvær, þær er eggjum verpa. Eggin eru eigi ger með hamri eða höndum, en þjónustumeyjar báru ölit í eggskurninni.",
          "Gestumblindi mælti: \"Liðar verðr sá at leita, er lítit sax hefir ok mjök er fáfróðr, ok vilda ek enn tala fleira, eða\""
        ],
        "placeholder": false
      },
      {
        "id": "36",
        "type": "stanza",
        "number": "18.",
        "lines": [
          "\"Hverjar eru þær rýgjar",
          "á reginfjalli,",
          "elr við kván kona,",
          "mær við meyju",
          "mög of getr,",
          "ok eigu-t þær varðir vera?",
          "Heiðrekr konungr,",
          "hygg þú at gátu.",
          "Góð er gáta þín,",
          "Gestumblindi,",
          "getit er þeirar:\""
        ],
        "placeholder": false
      },
      {
        "id": "37",
        "type": "prose",
        "number": "",
        "lines": [
          "Þat eru fjallhvannir tvær saman, ok rennr upp hvannkálfr í millum þeira.",
          "Gestumblindi mælti:"
        ],
        "placeholder": false
      },
      {
        "id": "38",
        "type": "stanza",
        "number": "19.",
        "lines": [
          "\"Hverjar eru þær snótir,",
          "er um sinn dróttin",
          "vápnlausar vega,",
          "inar jörpu hlífa",
          "um alla daga,",
          "en inar fegri frýja?",
          "Heiðrekr konungr,",
          "hygg þú at gátu.",
          "Góð er gáta þín,",
          "Gestumblindi,",
          "getit er þeirar:\""
        ],
        "placeholder": false
      },
      {
        "id": "39",
        "type": "prose",
        "number": "",
        "lines": [
          "Þat er hneftafl. Töflur drepast vápnlausar um hnefann, ok fylgja honum inar rauðu."
        ],
        "placeholder": false
      },
      {
        "id": "40",
        "type": "stanza",
        "number": "20.",
        "lines": [
          "\"Hverjar eru þær leikur,",
          "er líða lönd yfir",
          "at forvitni föður,",
          "hvítan skjöld",
          "þær á vetrum bera,",
          "en svartan um sumar?",
          "Heiðrekr konungr,",
          "hygg þú at gátu.\""
        ],
        "placeholder": false
      },
      {
        "id": "41",
        "type": "prose",
        "number": "",
        "lines": [
          "Þat eru rjúpur. Þær eru hvítar um vetr, en svartar um sumar.",
          "Gestumblindi mælti:"
        ],
        "placeholder": false
      },
      {
        "id": "42",
        "type": "stanza",
        "number": "21.",
        "lines": [
          "\"Hverjar eru þær snótir,",
          "er ganga syrgjandi",
          "at forvitni föður,",
          "hadda bleika hafa þær",
          "inar hvítföldnu",
          "ok eigu í vindi at vaxa?",
          "Heiðrekr konungr,",
          "hygg þú at gátu.",
          "Góð er gáta þín,",
          "Gestumblindi,",
          "getit er þeirar:\""
        ],
        "placeholder": false
      },
      {
        "id": "43",
        "type": "prose",
        "number": "",
        "lines": [
          "Þat eru bylgjur, er heita Ægismeyjar.",
          "Gestumblindi mælti:"
        ],
        "placeholder": false
      },
      {
        "id": "44",
        "type": "stanza",
        "number": "22.",
        "lines": [
          "\"Hverjar eru þær meyjar,",
          "er ganga margar saman",
          "at forvitni föður,",
          "mörgum hafa manni",
          "þær at meini komit",
          "ok eigu-t þær varðir vera?",
          "Heiðrekr konungr,",
          "hygg þú at gátu.",
          "Góð er gáta þín,",
          "Gestumblindi,",
          "getit er þeirar:\""
        ],
        "placeholder": false
      },
      {
        "id": "45",
        "type": "prose",
        "number": "",
        "lines": [
          "en þetta eru bárur sem áðan.",
          "Gestumblindi mælti:"
        ],
        "placeholder": false
      },
      {
        "id": "46",
        "type": "stanza",
        "number": "23.",
        "lines": [
          "\"Hverjar eru þær brúðir,",
          "er ganga brimserkjum í",
          "ok eigu eftir firði för,",
          "harðan beð hafa þær",
          "inar hvítföldnu",
          "ok leika í logni fátt?",
          "Heiðrekr konungr,",
          "hygg þú at gátu.",
          "Góð er gáta þín,",
          "Gestumblindi,",
          "getit er þeirar:\""
        ],
        "placeholder": false
      },
      {
        "id": "47",
        "type": "prose",
        "number": "",
        "lines": [
          "Þat eru enn Ægis meyjar, ok förlast þér nú mjök framburðurinn, ok muntu nú vilja þola dóm spekinga.",
          "Gestumblindi segir: \"Tregr em ek þess, en þó væntir mik, at þar komi nú skjótt.\""
        ],
        "placeholder": false
      },
      {
        "id": "48",
        "type": "stanza",
        "number": "24.",
        "lines": [
          "\"Fara ek sá",
          "foldar moldbúa,",
          "á sat nár á nái,",
          "blindr reið blindum",
          "brimreiðar til,",
          "jór er andar vanr.",
          "Heiðrekr konungr,",
          "hygg þú at gátu.",
          "Góð er gáta þín,",
          "Gestumblindi,",
          "getit er þeirar:\""
        ],
        "placeholder": false
      },
      {
        "id": "49",
        "type": "prose",
        "number": "",
        "lines": [
          "Þar komtu at á einni, ok rak ísjaka eftir ánni, ok lá þar dauðr hestr ok á hestinum einn dauðr ormr, ok bar þar blindr blindan, er þeir váru þrír saman.",
          "Gestumblindi mælti:"
        ],
        "placeholder": false
      },
      {
        "id": "50",
        "type": "stanza",
        "number": "25.",
        "lines": [
          "\"Hvat er þat dýra,",
          "er drepr fé manna",
          "ok er járni kringt útan,",
          "horn hefir átta,",
          "en höfuð ekki",
          "ok rennr, sem renna má?",
          "Heiðrekr konungr,",
          "hygg þú at gátu.",
          "Góð er gáta þín,",
          "Gestumblindi,",
          "getit er þeirar:\""
        ],
        "placeholder": false
      },
      {
        "id": "51",
        "type": "prose",
        "number": "",
        "lines": [
          "Þat er húnn í hneftafli; hann heitir sem björn; hann rennr, þegar honum er kastat.",
          "Gestumblindi mælti:"
        ],
        "placeholder": false
      },
      {
        "id": "52",
        "type": "stanza",
        "number": "26.",
        "lines": [
          "\"Hvat er þat dýra,",
          "er Dönum hlífir,",
          "berr blóðugt bak,",
          "en bergr firum,",
          "geirum mætir,",
          "gefr líf sumum,",
          "leggr við lófa",
          "lík sitt gumi?",
          "Heiðrekr konungr,",
          "hygg þú at gátu.",
          "Góð er gáta þín,",
          "Gestumblindi,",
          "getit er þeirar:\""
        ],
        "placeholder": false
      },
      {
        "id": "53",
        "type": "prose",
        "number": "",
        "lines": [
          "Þat er skjöldr; hann bergr mörgum; hann berr oft blóðugt bak.",
          "Gestumblindi mælti:"
        ],
        "placeholder": false
      },
      {
        "id": "54",
        "type": "stanza",
        "number": "27.",
        "lines": [
          "\"Mjök varp forðum",
          "nösgás vaxin,",
          "barngjörn sú er bar",
          "bútimbr saman,",
          "hlífðu henni",
          "hálms bitskálmir,",
          "þó lá drykkjar",
          "drynhraun yfir.",
          "Heiðrekr konungr,",
          "hygg þú at gátu.",
          "Góð er gáta þín,",
          "Gestumblindi,",
          "getit er þeirar:\""
        ],
        "placeholder": false
      },
      {
        "id": "55",
        "type": "prose",
        "number": "",
        "lines": [
          "Þar lá önd á eggjum millum nautskjálka, er þú hálms bitskálmir kallar, en drynhraun hausinn, en bútimbr hreiðrit."
        ],
        "placeholder": false
      },
      {
        "id": "56",
        "type": "stanza",
        "number": "28.",
        "lines": [
          "\"Fjórir ganga,",
          "fjórir hanga,",
          "tveir veg vísa,",
          "tveir hundum varða,",
          "einn eftir drallar",
          "ok oftast óhreinn.",
          "Heiðrekr konungr,",
          "hygg þú at gátu.",
          "Góð er gáta þín,",
          "Gestumblindi,",
          "getit er þeirar:\""
        ],
        "placeholder": false
      },
      {
        "id": "57",
        "type": "prose",
        "number": "",
        "lines": [
          "Þat er kýr; hon hefir fjóra fætr ok fjóra spena, tvau horn ok tvau augu, en halinn drallar eftir.",
          "Gestumblindi mælti:"
        ],
        "placeholder": false
      },
      {
        "id": "58",
        "type": "stanza",
        "number": "29.",
        "lines": [
          "\"Hverr er sá inn eini,",
          "er sefr í öskugrúa",
          "ok er af grjóti einu gerr,",
          "föður né móður",
          "á-at sá inn fárgjarni,",
          "þar mun hann sinn aldr ala?",
          "Heiðrekr konungr,",
          "hygg þú at gátu.",
          "Góð er gáta þín,",
          "Gestumblindi,",
          "getit er þeirar:\""
        ],
        "placeholder": false
      },
      {
        "id": "59",
        "type": "prose",
        "number": "",
        "lines": [
          "Þat er fólginn eldr á arni, er drepinn er við tinnu.",
          "Gestumblindi mælti:"
        ],
        "placeholder": false
      },
      {
        "id": "60",
        "type": "stanza",
        "number": "30.",
        "lines": [
          "\"Hest sá ek standa,",
          "hýddi meri,",
          "dúði dindil,",
          "drap hlaun und kvið,",
          "ór skal draga",
          "ok gjöfta at góða stund.",
          "Heiðrekr konungr,",
          "hygg þú at gátu.\""
        ],
        "placeholder": false
      },
      {
        "id": "61",
        "type": "prose",
        "number": "",
        "lines": [
          "Þá svarar konungr: \"Þessa gátu skulu ráða hirðmenn mínir.\"",
          "Þeir gátu margs til ok eigi fagrs mjök.",
          "Þá mælti konungr, sem hann sá, at þeir gerðu ekki at: \"Hest þann kallar þú línvef, en skeið meri hans, er upp ok ofan skal hrista vefinn.\"",
          "Gestumblindi mælti:"
        ],
        "placeholder": false
      },
      {
        "id": "62",
        "type": "stanza",
        "number": "31.",
        "lines": [
          "\"Hverir eru þeir þegnar,",
          "er ríða þingi at",
          "ok eru sextán saman,",
          "lýði sína",
          "senda þeir lönd yfir",
          "at byggja bólstaði.",
          "Heiðrekr konungr,",
          "hygg þú at gátu.",
          "Góð er gáta þín,",
          "Gestumblindi,",
          "getit er þeirar:\""
        ],
        "placeholder": false
      },
      {
        "id": "63",
        "type": "prose",
        "number": "",
        "lines": [
          "Þat er tafl Ítreks konungs.",
          "Gestumblindi mælti:"
        ],
        "placeholder": false
      },
      {
        "id": "64",
        "type": "stanza",
        "number": "32.",
        "lines": [
          "\"Sá ek á sumri",
          "sólbjörgum í",
          "verðung vaka",
          "vilgi teita,",
          "drukku jarlar",
          "öl þegjandi,",
          "en æpanda",
          "ölker stóð.",
          "Heiðrekr konungr,",
          "hygg þú at gátu.",
          "Góð er gáta þín,",
          "Gestumblindi,",
          "getit er þeirar:\""
        ],
        "placeholder": false
      },
      {
        "id": "65",
        "type": "prose",
        "number": "",
        "lines": [
          "Þat er grísa sýr; þá er grísir sjúga hana, þá hrínn hon, er þeir þegja. En eigi veit ek, hverr manna þú ert, er þvílíka hluti gerir svá mjúkliga af litlum efnum. Ok nú biðr konungr í hljóði, at byrgja skal hallardyrnar.",
          "Gestumblindi mælti:"
        ],
        "placeholder": false
      },
      {
        "id": "66",
        "type": "stanza",
        "number": "33.",
        "lines": [
          "\"Meyjar ek sá",
          "moldu líkar,",
          "váru þeim at beðjum björg,",
          "svartar ok sámar",
          "í sólviðri,",
          "en þess at fegri er færa of sér.",
          "Heiðrekr konungr,",
          "hygg þú at gátu.",
          "Góð er gáta þín,",
          "Gestumblindi,",
          "getit er þeirar:\""
        ],
        "placeholder": false
      },
      {
        "id": "67",
        "type": "prose",
        "number": "",
        "lines": [
          "Þat eru glæður fölnaðar á arni.",
          "Gestumblindi mælti:"
        ],
        "placeholder": false
      },
      {
        "id": "68",
        "type": "stanza",
        "number": "34.",
        "lines": [
          "\"Sat ek á segli,",
          "sá ek dauða menn",
          "blóðugt hold bera",
          "í börk viðar.",
          "Heiðrekr konungr,",
          "hygg þú at gátu.",
          "Góð er gáta þín,",
          "Gestumblindi,",
          "getit er þeirar:\""
        ],
        "placeholder": false
      },
      {
        "id": "69",
        "type": "prose",
        "number": "",
        "lines": [
          "Þar saztu á vegg, sáttu val fljúga ok bar æði í klóm sér.",
          "Gestumblindi mælti:"
        ],
        "placeholder": false
      },
      {
        "id": "70",
        "type": "stanza",
        "number": "35.",
        "lines": [
          "\"Hverir eru þeir tveir,",
          "er tíu hafa fætr,",
          "augu þrjú",
          "ok einn hala?",
          "Heiðrekr konungr,",
          "hygg þú at gátu.",
          "Góð er gáta þín,",
          "Gestumblindi,",
          "getit er þeirar:\""
        ],
        "placeholder": false
      },
      {
        "id": "71",
        "type": "prose",
        "number": "",
        "lines": [
          "Margs freistar þú nú, er þú finnr þau rök til framburðar við mik, er forðum váru. Þat er þá er Óðinn reið hestinum Sleipni. Hann hafði átta fætr, en Óðinn tvá, en þeir höfðu þrjú augu, Sleipnir tvau, en Óðinn eitt.",
          "Gestumblindi mælti:"
        ],
        "placeholder": false
      },
      {
        "id": "72",
        "type": "stanza",
        "number": "36.",
        "lines": [
          "\"Segðu þat þá hinzt,",
          "ef þú, Heiðrekr, ert",
          "hverjum vitrari vísa:",
          "Hvat mælti Óðinn",
          "í eyra Baldri,",
          "áðr hann var á bál hafðr?\""
        ],
        "placeholder": false
      },
      {
        "id": "73",
        "type": "prose",
        "number": "",
        "lines": [
          "Konungr svarar:"
        ],
        "placeholder": false
      },
      {
        "id": "74",
        "type": "stanza",
        "number": "37.",
        "lines": [
          "\"Undr ok argskap",
          "ok alla bleyði,",
          "(vænti ek verit hafa,",
          "en orð þau, er mæltir,",
          "einn þú veizt),",
          "ill vættr ok örm.\""
        ],
        "placeholder": false
      },
      {
        "id": "75",
        "type": "prose",
        "number": "",
        "lines": [
          "Konungr brá þá Tyrfingi ok hjó til Gestumblinda, en hann brást í vals líki ok fló út gegnum hallarglugg einn. En sverðit kom á vélit valsins, ok er hann því vélstuttr jafnan síðan, svá sem heiðnir menn trúa. Ok var nú Óðinn honum reiðr orðinn, síðan hann hjó til hans, ok á þeiri nótt var konungr drepinn."
        ],
        "placeholder": false
      }
    ],
    "ru": [
      {
        "id": "1",
        "type": "prose",
        "number": "",
        "lines": [
          "Одного человека звали Гестумблинди, могучего и великого недруга конунга Хейдрека. Конунг послал ему сообщение, чтобы он пришел на встречу с ним для примирения, если он хочет спасти свою жизнь. Гестумблинди не был большим мудрецом, поскольку он считал себя неспособным обменяться словами с конунгом; он также знал, что будет тяжело полагаться на суд мудрецов, так как обвинения серьезны, и он решил, исходя из своих интересов, принести жертву Одину, попросить его рассмотреть свое дело и обещал ему большое вознаграждение.",
          "Однажды поздно вечером в дверь постучали, Гестумблинди подходит к двери и видит входящего человека. Он спрашивает, как его зовут, а тот назвался Гестумблинди и сказал, что они должны обменяться одеждой, и так они и делают. Крестьянин уходит и прячется, а пришедший входит, и всем кажется, что они узнают Гестумблинди, и так проходит ночь.",
          "На следующий день Гестумблинди едет на встречу с конунгом; он приветствовал конунга. Конунг молчал.",
          "Господин, — говорит он, — я пришел сюда для примирения с вами.",
          "Тогда конунг спрашивает: Ты хочешь подвергнуться суду моих мудрецов?",
          "Он говорит: Есть ли другие способы выкупа?",
          "Король сказал: Их должно быть много, если ты готов предложить загадки.",
          "Гестумблинди говорит: Мало я к этому способен, но у меня нет иного выбора.",
          "Может быть, ты хочешь, — говорит король, — подвергнуться суду моих мудрецов?",
          "Лучше я выбираю загадывание загадок, — говорит он.",
          "Правильно, это подойдет, — говорит конунг.",
          "Тогда сказал Гестумблинди:"
        ],
        "placeholder": false
      },
      {
        "id": "2",
        "type": "stanza",
        "number": "1.",
        "lines": [
          "\"Иметь хочу я,",
          "то, что я имел вчера,",
          "узнай, что это было:",
          "людей сокрушающий,",
          "словам мешающий",
          "и слова вызывающий.",
          "Хейдрек конунг,",
          "подумай над загадкой!\""
        ],
        "placeholder": false
      },
      {
        "id": "3",
        "type": "prose",
        "number": "",
        "lines": [
          "Конунг говорит: Хороша твоя загадка, Гестумблинди, она отгадана. Пусть принесут ему пиво. Оно сокрушает у многих ум, а многие становятся более разговорчивыми, когда подносят пиво, а у многих заплетается язык, так что не хватает слов.",
          "Тогда сказал Гестумблинди:"
        ],
        "placeholder": false
      },
      {
        "id": "4",
        "type": "stanza",
        "number": "2.",
        "lines": [
          "\"Домой я ехал,",
          "домой я направлялся,",
          "увидел я на дороге дороги:",
          "была им дорога внизу",
          "и дорога вверху,",
          "и дорога на всех дорогах.",
          "Хейдрек конунг,",
          "подумай над загадкой!\""
        ],
        "placeholder": false
      },
      {
        "id": "5",
        "type": "prose",
        "number": "",
        "lines": [
          "Хороша твоя загадка, Гестумблинди, она отгадана. Там ты ехал по мосту через реку, и была дорога реки под тобой, а птицы летели над твоей головой и рядом с тобой с двух сторон, и это была их дорога.",
          "Тогда сказал Гестумблинди:"
        ],
        "placeholder": false
      },
      {
        "id": "6",
        "type": "stanza",
        "number": "3.",
        "lines": [
          "\"Что это из напитков,",
          "которые я вчера пил:",
          "это было ни вино, ни вода,",
          "и ни пиво,",
          "ни еда,",
          "и я ушел, утолив жажду,",
          "оттуда?",
          "Хейдрек конунг,",
          "подумай над загадкой!\""
        ],
        "placeholder": false
      },
      {
        "id": "7",
        "type": "prose",
        "number": "",
        "lines": [
          "Хороша твоя загадка, Гестумблинди, она отгадана. Ты лежал в тени, когда роса выпала на траву, и так охладились твои губы, и была утолена твоя жажда.",
          "Тогда сказал Гестумблинди:"
        ],
        "placeholder": false
      },
      {
        "id": "8",
        "type": "stanza",
        "number": "4.",
        "lines": [
          "\"Кто такой резкий,",
          "он идет по твердому пути",
          "и он раньше ходил,",
          "очень крепко целует,",
          "у него два рта",
          "и он ходит только по",
          "золоту?",
          "Хейдрек конунг,",
          "подумай над загадкой!\""
        ],
        "placeholder": false
      },
      {
        "id": "9",
        "type": "prose",
        "number": "",
        "lines": [
          "Хороша твоя загадка, Гестумблинди, она отгадана. Это молоток во время ковки золота: он громко разговаривает, когда он достигает твердой наковальни — это его путь.",
          "Тогда сказал Гестумблинди:"
        ],
        "placeholder": false
      },
      {
        "id": "10",
        "type": "stanza",
        "number": "5.",
        "lines": [
          "\"Что это из чудес,",
          "которое я видел снаружи",
          "перед дверью Деллинга?",
          "Двое неживых,",
          "лишенных дыхания",
          "кипятили чеснок ран?",
          "Хейдрек конунг,",
          "подумай над загадкой!\""
        ],
        "placeholder": false
      },
      {
        "id": "11",
        "type": "prose",
        "number": "",
        "lines": [
          "Хороша твоя загадка, Гестумблинди, она отгадана. Это кузнечные меха: у них нет ветра, если они не надуты, и они мертвы, как любое другое изделие; на них можно выковать как меч, так и что-либо другое",
          "Тогда сказал Гестумблинди:"
        ],
        "placeholder": false
      },
      {
        "id": "12",
        "type": "stanza",
        "number": "6.",
        "lines": [
          "\"Что это из чудес,",
          "которое я видел снаружи",
          "перед дверью Деллинга?",
          "У него восемь ног,",
          "четыре глаза",
          "и живот над коленом.",
          "Хейдрек конунг,",
          "подумай над загадкой!\""
        ],
        "placeholder": false
      },
      {
        "id": "13",
        "type": "prose",
        "number": "",
        "lines": [
          "Это паук.",
          "Тогда сказал Гестумблинди:"
        ],
        "placeholder": false
      },
      {
        "id": "14",
        "type": "stanza",
        "number": "7.",
        "lines": [
          "\"Что это из чудес,",
          "которое я видел снаружи",
          "перед дверью Деллинга?",
          "Головой указывает",
          "на путь в хель,",
          "а ногами повернут к",
          "солнцу?",
          "Хейдрек конунг,",
          "подумай над загадкой!\""
        ],
        "placeholder": false
      },
      {
        "id": "15",
        "type": "prose",
        "number": "",
        "lines": [
          "Хороша твоя загадка, Гестумблинди, она отгадана. Это чеснок. Его голова крепко сидит в земле, и он распространяет ветки во время роста.",
          "Тогда сказал Гестумблинди:"
        ],
        "placeholder": false
      },
      {
        "id": "16",
        "type": "stanza",
        "number": "8.",
        "lines": [
          "\"Что это за чудо",
          "я видел снаружи",
          "перед дверью Деллинга?",
          "Рога тверже,",
          "ворона чернее,",
          "щита белее,",
          "рукоятки прямее?",
          "Хейдрек конунг,",
          "подумай над загадкой!\""
        ],
        "placeholder": false
      },
      {
        "id": "17",
        "type": "prose",
        "number": "",
        "lines": [
          "Хейдрек сказал: Теперь загадки становятся неинтересными. Зачем над ними сидеть? Это обсидиан, и на него светят лучи солнца.",
          "Тогда сказал Гестумблинди:"
        ],
        "placeholder": false
      },
      {
        "id": "18",
        "type": "stanza",
        "number": "9.",
        "lines": [
          "\"Несли жены",
          "светловолосые,",
          "служанки две",
          "пиво к скамьям;",
          "это было ни руками",
          "сделано,",
          "ни молотком сколочено,",
          "но был снаружи острова",
          "прямым тот, кто сделал.",
          "Хейдрек конунг,",
          "подумай над загадкой!\""
        ],
        "placeholder": false
      },
      {
        "id": "19",
        "type": "prose",
        "number": "",
        "lines": [
          "Хороша твоя загадка, Гестумблинди, она отгадана. Там жены лебедей направляются к своему гнезду и откладывают яйца; скорлупа яйца не сделана руками и не сколочена молотком, а лебедь перед островом, от которого у них дети, прямой.",
          "Тогда сказал Гестумблинди:"
        ],
        "placeholder": false
      },
      {
        "id": "20",
        "type": "stanza",
        "number": "10.",
        "lines": [
          "\"Что это за великанши",
          "на горе богов?",
          "Женщина рождает от",
          "женщины сына",
          "и нет у них защиты от",
          "мужей.",
          "Хейдрек конунг,",
          "подумай над загадкой!\""
        ],
        "placeholder": false
      },
      {
        "id": "21",
        "type": "prose",
        "number": "",
        "lines": [
          "Хороша твоя загадка, Гестумблинди, она отгадана. Это два дягиля и стебель дягиля между ними.",
          "Тогда сказал Гестумблинди:"
        ],
        "placeholder": false
      },
      {
        "id": "22",
        "type": "stanza",
        "number": "11.",
        "lines": [
          "\"Я видел, как",
          "передвигались",
          "по земле жители тверди:",
          "змей сидел на мертвеце.",
          "Слепой скакал на слепом",
          "к морю,",
          "а конь был бездыханным.",
          "Хейдрек конунг,",
          "подумай над загадкой!\""
        ],
        "placeholder": false
      },
      {
        "id": "23",
        "type": "prose",
        "number": "",
        "lines": [
          "Хороша твоя загадка, Гестумблинди, она отгадана. Там ты нашел на льдине мертвого коня и мертвого змея на коне, и они все вместе мчались к реке.",
          "Тогда сказал Гестумблинди:"
        ],
        "placeholder": false
      },
      {
        "id": "24",
        "type": "stanza",
        "number": "12.",
        "lines": [
          "\"Что за слуги",
          "скачут на тинг",
          "все вместе",
          "примирившиеся?",
          "Своих людей",
          "они посылают через",
          "страны",
          "чтобы жить в доме.",
          "Хейдрек конунг,",
          "подумай над загадкой!\""
        ],
        "placeholder": false
      },
      {
        "id": "25",
        "type": "prose",
        "number": "",
        "lines": [
          "Хороша твоя загадка, Гестумблинди, она отгадана. Это Итрек и Андад, играющие в тавлеи.",
          "Тогда сказал Гестумблинди:"
        ],
        "placeholder": false
      },
      {
        "id": "26",
        "type": "stanza",
        "number": "13.",
        "lines": [
          "\"Что за жены",
          "сражаются со своим",
          "безоружным господином?",
          "Более темные",
          "всегда защищают,",
          "а более светлые нападают.",
          "Хейдрек конунг,",
          "подумай над загадкой!\""
        ],
        "placeholder": false
      },
      {
        "id": "27",
        "type": "prose",
        "number": "",
        "lines": [
          "Хороша твоя загадка, Гестумблинди, она отгадана. Это шашки: темные защищают короля, а светлые нападают.",
          "Тогда сказал Гестумблинди:"
        ],
        "placeholder": false
      },
      {
        "id": "28",
        "type": "stanza",
        "number": "14.",
        "lines": [
          "\"Кто этот один,",
          "спящий в углублении",
          "очага,",
          "сделанном из одного",
          "камня;",
          "ни отца, ни матери",
          "нет у жаждущего блеска,",
          "там он должен жить.",
          "Хейдрек конунг,",
          "подумай над загадкой!\""
        ],
        "placeholder": false
      },
      {
        "id": "29",
        "type": "prose",
        "number": "",
        "lines": [
          "Это огонь, прячущийся в очаге и загорающийся от огнива.",
          "Тогда сказал Гестумблинди:"
        ],
        "placeholder": false
      },
      {
        "id": "30",
        "type": "stanza",
        "number": "15.",
        "lines": [
          "\"Кто это великий,",
          "проходящий над землей,",
          "он глотает воду и лес,",
          "бури он боится,",
          "но не людей",
          "и затевает ссору с солнцем.",
          "Хейдрек конунг,",
          "подумай над загадкой!\""
        ],
        "placeholder": false
      },
      {
        "id": "31",
        "type": "prose",
        "number": "",
        "lines": [
          "Хороша твоя загадка, Гестумблинди, она отгадана. Это тьма: она проходит над землей, так что из-за нее не видно солнца, а когда она уходит, сразу же начинается ветер.",
          "Тогда сказал Гестумблинди:"
        ],
        "placeholder": false
      },
      {
        "id": "32",
        "type": "stanza",
        "number": "16.",
        "lines": [
          "\"Кто это из зверей",
          "убивает скот людей",
          "и окружен снаружи",
          "железом?",
          "У него восемь рогов,",
          "но нет головы,",
          "и многие сопровождают",
          "его поэтому.",
          "Хейдрек конунг,",
          "подумай над загадкой!\""
        ],
        "placeholder": false
      },
      {
        "id": "33",
        "type": "prose",
        "number": "",
        "lines": [
          "Это король в игре в шашки.",
          "Тогда сказал Гестумблинди:"
        ],
        "placeholder": false
      },
      {
        "id": "34",
        "type": "stanza",
        "number": "17.",
        "lines": [
          "\"Кто это из зверей",
          "защищает датчан,",
          "несет кровавую спину,",
          "спасает людей,",
          "кормится копьями,",
          "некоторым дает жизнь,",
          "помещает тело и",
          "ладонь человека",
          "по разные стороны?",
          "Хейдрек конунг,",
          "подумай над загадкой!\""
        ],
        "placeholder": false
      },
      {
        "id": "35",
        "type": "prose",
        "number": "",
        "lines": [
          "Это щит: он часто становится кровавым в битве и хорошо защищает людей, искусных в обращении с щитом.",
          "Тогда сказал Гестумблинди:"
        ],
        "placeholder": false
      },
      {
        "id": "36",
        "type": "stanza",
        "number": "18.",
        "lines": [
          "\"Кто эти девицы,",
          "проходящие над землей",
          "к удивлению своего отца?",
          "Белый щит",
          "они носят зимой,",
          "а черный летом.\""
        ],
        "placeholder": false
      },
      {
        "id": "37",
        "type": "prose",
        "number": "",
        "lines": [
          "Это куропатки: они белые зимой, а черные летом.",
          "Тогда сказал Гестумблинди:"
        ],
        "placeholder": false
      },
      {
        "id": "38",
        "type": "stanza",
        "number": "19.",
        "lines": [
          "\"Кто эти женщины,",
          "идущие печально",
          "к удивлению своего отца?",
          "Многим людям",
          "они принесли беду,",
          "и так они должны",
          "прожить жизнь.",
          "Хейдрек конунг,",
          "подумай над загадкой!\""
        ],
        "placeholder": false
      },
      {
        "id": "39",
        "type": "prose",
        "number": "",
        "lines": [
          "Это жены Хлера; так их называют.",
          "Тогда сказал Гестумблинди:"
        ],
        "placeholder": false
      },
      {
        "id": "40",
        "type": "stanza",
        "number": "20.",
        "lines": [
          "\"Кто эти девы,",
          "идущие во множестве",
          "вместе",
          "к удивлению своего отца?",
          "Белые волосы",
          "у них, носящих белые",
          "головные уборы,",
          "и нет у них защиты",
          "мужей.\""
        ],
        "placeholder": false
      },
      {
        "id": "41",
        "type": "prose",
        "number": "",
        "lines": [
          "Это волны, так их называют.",
          "Тогда сказал Гестумблинди:"
        ],
        "placeholder": false
      },
      {
        "id": "42",
        "type": "stanza",
        "number": "21.",
        "lines": [
          "\"Кто эти вдовы,",
          "идущие все вместе,",
          "к удивлению своего отца?",
          "Редко они благосклонны",
          "к отряду воинов;",
          "они должны бодрствовать",
          "на ветру.",
          "Хейдрек конунг,",
          "подумай над загадкой!\""
        ],
        "placeholder": false
      },
      {
        "id": "43",
        "type": "prose",
        "number": "",
        "lines": [
          "Это вдовы Эгира, так называются волны.",
          "Тогда сказал Гестумблинди:"
        ],
        "placeholder": false
      },
      {
        "id": "44",
        "type": "stanza",
        "number": "22.",
        "lines": [
          "\"Давно выросла",
          "носатая гусыня,",
          "она чадолюбивая",
          "построила жилище.",
          "Ее защищали",
          "кусающие мечи соломы,",
          "а над ней находилась",
          "мычащая скала напитка.\""
        ],
        "placeholder": false
      },
      {
        "id": "45",
        "type": "prose",
        "number": "",
        "lines": [
          "Там утка устроила гнездо между челюстей быка, а над ним лежал череп.",
          "Тогда сказал Гестумблинди:"
        ],
        "placeholder": false
      },
      {
        "id": "46",
        "type": "stanza",
        "number": "23.",
        "lines": [
          "\"Кто этот великий,",
          "многими правящий,",
          "наполовину повернутый",
          "к хель?",
          "Он спасает людей",
          "и ссорится с землей,",
          "если у него есть",
          "надежный друг.",
          "Хейдрек конунг,",
          "подумай над загадкой!\""
        ],
        "placeholder": false
      },
      {
        "id": "47",
        "type": "prose",
        "number": "",
        "lines": [
          "Хороша твоя загадка, Гестумблинди, она отгадана. Это якорь с хорошим канатом: если его лапа на дне, он спасает.",
          "Тогда сказал Гестумблинди:"
        ],
        "placeholder": false
      },
      {
        "id": "48",
        "type": "stanza",
        "number": "24.",
        "lines": [
          "\"Кто эти жены,",
          "идущие к скалам прибоя,",
          "совершающие путешествие",
          "за путешествием?",
          "Твердое ложе",
          "у женщин в белых",
          "головных уборах;",
          "они мало играют",
          "в затишье.\""
        ],
        "placeholder": false
      },
      {
        "id": "49",
        "type": "prose",
        "number": "",
        "lines": [
          "Это волны, их ложе — это шхеры и груды камней; они уменьшаются в затишье.",
          "Тогда сказал Гестумблинди:"
        ],
        "placeholder": false
      },
      {
        "id": "50",
        "type": "stanza",
        "number": "25.",
        "lines": [
          "\"Видел я летом",
          "на закате,",
          "приветствовал я",
          "очень веселых:",
          "пили ярлы",
          "молча пиво,",
          "и крича",
          "стояла пивная кружка.",
          "Хейдрек конунг,",
          "подумай над загадкой!\""
        ],
        "placeholder": false
      },
      {
        "id": "51",
        "type": "prose",
        "number": "",
        "lines": [
          "Там пили поросята молоко у свиньи, а она визжала.",
          "Тогда сказал Гестумблинди:"
        ],
        "placeholder": false
      },
      {
        "id": "52",
        "type": "stanza",
        "number": "26.",
        "lines": [
          "\"Что это за чудо",
          "я видел снаружи",
          "перед дверью Деллинга?",
          "У него десять языков,",
          "двадцать глаз,",
          "сорок ног,",
          "оно продвигается вперед.",
          "Хейдрек конунг,",
          "подумай над загадкой!\""
        ],
        "placeholder": false
      },
      {
        "id": "53",
        "type": "prose",
        "number": "",
        "lines": [
          "Тогда король сказал: Если ты тот самый Гестумблинди, как я думал, то ты умнее, чем я полагал. Ты говоришь о свинье во дворе.",
          "Тогда конунг велел убить свинью, и внутри у нее оказалось девять поросят, как сказал Гестумблинди. Король заподозрил, кем должен быть этот человек.",
          "Тогда сказал Гестумблинди:"
        ],
        "placeholder": false
      },
      {
        "id": "54",
        "type": "stanza",
        "number": "27.",
        "lines": [
          "\"Четыре висят,",
          "четыре идут,",
          "два указывают путь,",
          "два защищаются от собак,",
          "один болтается",
          "всегда грязный.",
          "Хейдрек конунг,",
          "подумай над загадкой!\""
        ],
        "placeholder": false
      },
      {
        "id": "55",
        "type": "prose",
        "number": "",
        "lines": [
          "Хороша твоя загадка, Гестумблинди, она отгадана. Это корова.",
          "Тогда сказал Гестумблинди:"
        ],
        "placeholder": false
      },
      {
        "id": "56",
        "type": "stanza",
        "number": "28.",
        "lines": [
          "\"Сидел я на стене,",
          "видел я, как мертвецы",
          "несли кровавое тело",
          "в коре дерева.\""
        ],
        "placeholder": false
      },
      {
        "id": "57",
        "type": "prose",
        "number": "",
        "lines": [
          "Ты сидел на стене и видел, как гага несла падаль в скалу.",
          "Тогда сказал Гестумблинди:"
        ],
        "placeholder": false
      },
      {
        "id": "58",
        "type": "stanza",
        "number": "29.",
        "lines": [
          "\"Кто эти двое?",
          "У них десять ног,",
          "три глаза",
          "и один хвост.",
          "Хейдрек конунг,",
          "подумай над загадкой!\""
        ],
        "placeholder": false
      },
      {
        "id": "59",
        "type": "prose",
        "number": "",
        "lines": [
          "Это Один скачет на Слейпнире.",
          "Тогда сказал Гестумблинди:"
        ],
        "placeholder": false
      },
      {
        "id": "60",
        "type": "stanza",
        "number": "30.",
        "lines": [
          "\"Скажи последнее,",
          "если ты мудрее любого",
          "конунга:",
          "что сказал Один",
          "в ухо Бальдру,",
          "пока его не подняли на",
          "погребальный костер?\""
        ],
        "placeholder": false
      },
      {
        "id": "61",
        "type": "prose",
        "number": "",
        "lines": [
          "Хейдрек конунг говорит: \"Это знаешь ты один, женоподобное существо!\"",
          "И тогда Хейдрек выхватил меч Тюрфинг и ударил его, а Один принял облик сокола и улетел. А король замахнулся в след его хвостовому оперенью, и поэтому сокол с тех пор короткохвостый.",
          "Тогда Один сказал: \"За то, что ты, конунг Хейдрек, ко мне несправедлив и хотел убить меня невиновного, тебя должны будут убить худшие из слуг.\"",
          "После этого он расстался с ним."
        ],
        "placeholder": false
      }
    ],
    "en": [
      {
        "id": "1",
        "type": "prose",
        "number": "",
        "lines": [
          ""
        ],
        "placeholder": false
      },
      {
        "id": "2",
        "type": "stanza",
        "number": "1.",
        "lines": [
          "Gestumblindi said:",
          "\"That would I have which I had yesterday;",
          "heed what I had:",
          "men’s hamperer, word’s hinderer,",
          "and speeder of speech.",
          "Aright read now this riddle, Heithrek!\"",
          "Heithrek said:",
          "\"Good is thy riddle, Gestumblindi,",
          "and guessed it is:",
          "give him ale! That hampers many a man’s wits; by it,",
          "some become talkative, but other men’s wits are mazed.\""
        ],
        "placeholder": false
      },
      {
        "id": "3",
        "type": "prose",
        "number": "",
        "lines": [
          ""
        ],
        "placeholder": false
      },
      {
        "id": "4",
        "type": "stanza",
        "number": "2.",
        "lines": [
          "Gestumblindi said:",
          "\"From home I hied me, and from home faring",
          "I saw a way of ways:",
          "was a way beneath and a way above,",
          "and ways there were on all sides.",
          "Aright guess now this riddle, Heithrek!\"",
          "Heithrek said:",
          "\"Good is thy riddle, Gestumblindi,",
          "and guessed it is:",
          "You went over a bridge, the river ran under it, the birds flew above your head and on either side of you—that was their way.\""
        ],
        "placeholder": false
      },
      {
        "id": "5",
        "type": "prose",
        "number": "",
        "lines": [
          ""
        ],
        "placeholder": false
      },
      {
        "id": "6",
        "type": "stanza",
        "number": "3.",
        "lines": [
          "Gestumblindi said:",
          "\"What drink was it I drank yesterday?",
          "twas neither wine nor water,",
          "neither mead nor ale, nor meat, either;",
          "yet went I thirstless thence.",
          "Aright guess now this riddle, Heithrek!\"",
          "Heithrek said:",
          "\"Good is thy riddle, Gestumblindi,",
          "and guessed it is.",
          "you lay down in the shade where the dew had fallen on the grass, and this cooled your lips and quenched your thirst.\""
        ],
        "placeholder": false
      },
      {
        "id": "7",
        "type": "prose",
        "number": "",
        "lines": [
          ""
        ],
        "placeholder": false
      },
      {
        "id": "8",
        "type": "stanza",
        "number": "4.",
        "lines": [
          "Gestumblindi said:",
          "\"Harshly he clangs, on hard paths treading",
          "which he has fared before.",
          "Two mouths he has, and mightily kisses,",
          "and on gold alone he goes.",
          "Aright guess now this riddle, Heithrek!\"",
          "Heithrek said:",
          "\"Good is thy riddle, Gestumblindi,",
          "and guessed it is:",
          "that is the goldsmith’s hammer with which gold is beaten.\""
        ],
        "placeholder": false
      },
      {
        "id": "9",
        "type": "prose",
        "number": "",
        "lines": [
          ""
        ],
        "placeholder": false
      },
      {
        "id": "10",
        "type": "stanza",
        "number": "5.",
        "lines": [
          "Gestumblindi said:",
          "\"Who is the great one that glides o’er the earth,",
          "and swallows both waters and woods?",
          "The wind he fears, but wights nowise,",
          "and seeks to harm the sun.",
          "Aright guess now this riddle, Heithrek!\"",
          "Heithrek said:",
          "\"Good is thy riddle, Gestumblindi,",
          "and guessed it is:",
          "That is the fog. One cannot see the sun because of him, but he disappears when the wind blows, and men can do naught against him. He kills the light of the sun.\""
        ],
        "placeholder": false
      },
      {
        "id": "11",
        "type": "prose",
        "number": "",
        "lines": [
          ""
        ],
        "placeholder": false
      },
      {
        "id": "12",
        "type": "stanza",
        "number": "6.",
        "lines": [
          "Gestumblindi said:",
          "\"Who is the mighty one who o’er much has sway,",
          "the half of whom turns toward Hel?",
          "He saves many men but slashes the earth,",
          "if fast with trusty friend.",
          "Aright guess now this riddle, Heithrek!\"",
          "Heithrek said:",
          "\"Good is thy riddle, Gestumblindi,",
          "and guessed it is:",
          "That is the anchor, with a stout and strong rope. It guards many a ship. It grips the earth with one fluke which thus turns Hel-ward. Many a man has been saved by it.\""
        ],
        "placeholder": false
      },
      {
        "id": "13",
        "type": "prose",
        "number": "",
        "lines": [
          ""
        ],
        "placeholder": false
      },
      {
        "id": "14",
        "type": "stanza",
        "number": "7.",
        "lines": [
          "Gestumblindi said:",
          "\"On high fells what lives? What falls in deep dales?",
          "Without air what lives? What is not ever silent?",
          "Aright guess now this riddle, Heithrek!\"",
          "Heithrek said:",
          "\"Good is thy riddle, Gestumblindi,",
          "and guessed it is:",
          "the raven always lives on high fells, the dew always falls in deep dales, the fish live without air, and the roaring waterfall is never silent.\""
        ],
        "placeholder": false
      },
      {
        "id": "15",
        "type": "prose",
        "number": "",
        "lines": [
          ""
        ],
        "placeholder": false
      },
      {
        "id": "16",
        "type": "stanza",
        "number": "8.",
        "lines": [
          "Gestumblindi said:",
          "\"What marvel is it which without I saw,",
          "before Delling’s-door,",
          "with his head ever Hel-ward turning,",
          "with his feet seeking the sun.",
          "Aright guess now this riddle, Heithrek!\"",
          "Heithrek said:",
          "\"Good is thy riddle, Gestumblindi,",
          "and guessed it is:",
          "That is the leek: its head turns into the earth, but the leaves, upward.\""
        ],
        "placeholder": false
      },
      {
        "id": "17",
        "type": "prose",
        "number": "",
        "lines": [
          ""
        ],
        "placeholder": false
      },
      {
        "id": "18",
        "type": "stanza",
        "number": "9.",
        "lines": [
          "Gestumblindi said:",
          "\"What marvel is it which without I saw,",
          "before Delling’s-door?",
          "Were twain briskly, and breathless withal.",
          "boiling a wand-of-wounds.",
          "Aright guess now this riddle, Heithrek!\"",
          "Heithrek said:",
          "\"Good is thy riddle, Gestumblindi,",
          "and guessed it is:",
          "they are the smith’s bellows; they blow but have no breath.\""
        ],
        "placeholder": false
      },
      {
        "id": "19",
        "type": "prose",
        "number": "",
        "lines": [
          ""
        ],
        "placeholder": false
      },
      {
        "id": "20",
        "type": "stanza",
        "number": "10.",
        "lines": [
          "Gestumblindi said:",
          "\"What marvel is it which without I saw,",
          "before Delling’s-door?",
          "The white fliers on the flagstones bounded.",
          "but the swart ones sank in the sand.",
          "Aright guess now this riddle, Heithrek!\"",
          "Heithrek said:",
          "\"Good is thy riddle, Gestumblindi,",
          "and guessed it is:",
          "they are hail and rain; because the hail beats on the flags, but the rain drops sink in the sand and go into the ground.\""
        ],
        "placeholder": false
      },
      {
        "id": "21",
        "type": "prose",
        "number": "",
        "lines": [
          ""
        ],
        "placeholder": false
      },
      {
        "id": "22",
        "type": "stanza",
        "number": "11.",
        "lines": [
          "Gestumblindi said:",
          "\"What marvel is it which without I saw,",
          "before Delling’s-door?",
          "A black boar saw I bask in the mud,",
          "yet no bristles stood on his back.",
          "Aright guess now this riddle, Heithrek!\"",
          "Heithrek said:",
          "\"Good is thy riddle, Gestumblindi,",
          "and guessed it is:",
          "that is the dung-beetle.\""
        ],
        "placeholder": false
      },
      {
        "id": "23",
        "type": "prose",
        "number": "",
        "lines": [
          ""
        ],
        "placeholder": false
      },
      {
        "id": "24",
        "type": "stanza",
        "number": "12.",
        "lines": [
          "Gestumblindi said:",
          "\"What marvel is it which without I saw,",
          "before Delling’s-door?",
          "Ten tongues has it, has twenty eyes",
          "and forty feet, slowly fares that wight.",
          "Aright guess now this riddle, Heithrek!\"",
          "Heithrek said:",
          "\"Good is thy riddle, Gestumblindi,",
          "and guessed it is:",
          "you saw a sow in the farmyard with nine shoats in her. Then the king had the sow killed, and nine pigs were found in her, just as Gestumblindi had said.\""
        ],
        "placeholder": false
      },
      {
        "id": "25",
        "type": "prose",
        "number": "",
        "lines": [
          ""
        ],
        "placeholder": false
      },
      {
        "id": "26",
        "type": "stanza",
        "number": "13.",
        "lines": [
          "Gestumblindi said:",
          "\"What marvel is it which without I saw,",
          "before Delling’s-door?",
          "Upward it flies with eagle’s voice,",
          "and hard grip its claws the helmet.",
          "Aright guess now this riddle, Heithrek!\"",
          "Heithrek said:",
          "\"Good is thy riddle, Gestumblindi,",
          "and guessed it is:",
          "that is the arrow.\""
        ],
        "placeholder": false
      },
      {
        "id": "27",
        "type": "prose",
        "number": "",
        "lines": [
          ""
        ],
        "placeholder": false
      },
      {
        "id": "28",
        "type": "stanza",
        "number": "14.",
        "lines": [
          "Gestumblindi said:",
          "\"What marvel is it which without I saw,",
          "before Delling’s-door?",
          "Eight feet it has and four eyes,",
          "and its knees are above its belly.",
          "Aright guess now this riddle, Heithrek!\"",
          "Heithrek said:",
          "\"Good is thy riddle, Gestumblindi,",
          "and guessed it is:",
          "it is the spider.\""
        ],
        "placeholder": false
      },
      {
        "id": "29",
        "type": "prose",
        "number": "",
        "lines": [
          ""
        ],
        "placeholder": false
      },
      {
        "id": "30",
        "type": "stanza",
        "number": "15.",
        "lines": [
          "Gestumblindi said:",
          "\"What marvel is it which without I saw,",
          "before Delling’s-door?",
          "It lights for men, and swallows up lights,",
          "and wolves seek ever to win it.",
          "Aright guess now this riddle, Heithrek!\"",
          "Heithrek said:",
          "\"Good is thy riddle, Gestumblindi,",
          "and guessed it is:",
          "that is the Sun. He lights all the world and shines on all men; but there are two wolves, hight Skalli and Hatti, one of whom goes before, and the other follows, the sun.\""
        ],
        "placeholder": false
      },
      {
        "id": "31",
        "type": "prose",
        "number": "",
        "lines": [
          ""
        ],
        "placeholder": false
      },
      {
        "id": "32",
        "type": "stanza",
        "number": "16.",
        "lines": [
          "Gestumblindi said:",
          "\"What marvel is it which without I saw,",
          "before Delling’s-door?",
          "Harder than horn, blacker than Hel,",
          "whiter than shell of egg, straighter than shaft of spear.",
          "Aright guess now this riddle, Heithrek!\"",
          "Heithrek said:",
          "\"Good is thy riddle, Gestumblindi,",
          "and guessed it is:",
          "that is obsidian, with the sun shining on it.\""
        ],
        "placeholder": false
      },
      {
        "id": "33",
        "type": "prose",
        "number": "",
        "lines": [
          ""
        ],
        "placeholder": false
      },
      {
        "id": "34",
        "type": "stanza",
        "number": "17.",
        "lines": [
          "Gestumblindi said:",
          "\"Two brides did bear, white-blond their locks,",
          "and house-maids were they ale-casks homeward;",
          "were they not shaped by hand nor by hammers wrought;",
          "yet upright sate he on the isles, who made them.",
          "Aright guess now this riddle, Heithrek!\"",
          "Heithrek said:",
          "\"Good is thy riddle, Gestumblindi,",
          "and guessed it is:",
          "you saw two female swans going to their nests to lay their eggs. Their shells are neither hand-made nor wrought by hammers; but the he-swan sits out on the islands, he that gat their eggs with them.\""
        ],
        "placeholder": false
      },
      {
        "id": "35",
        "type": "prose",
        "number": "",
        "lines": [
          ""
        ],
        "placeholder": false
      },
      {
        "id": "36",
        "type": "stanza",
        "number": "18.",
        "lines": [
          "Gestumblindi said:",
          "\"Who be the women on wilding fell?",
          "One bears a babe by the other,",
          "and maid by maid a man-child begets,",
          "yet man has not touched these maids.",
          "Aright guess now this riddle, Heithrek!\"",
          "Heithrek said:",
          "\"Good is thy riddle, Gestumblindi,",
          "and guessed it is:",
          "they are two angelica stalks standing together, with a shoot coming up between them.\""
        ],
        "placeholder": false
      },
      {
        "id": "37",
        "type": "prose",
        "number": "",
        "lines": [
          ""
        ],
        "placeholder": false
      },
      {
        "id": "38",
        "type": "stanza",
        "number": "19.",
        "lines": [
          "Gestumblindi said:",
          "\"Who be the women who, weaponless,",
          "for their king kill each other?",
          "Every day the dark ones shield him,",
          "but the fair ones aye go forth.",
          "Aright guess now this riddle, Heithrek!\"",
          "Heithrek said:",
          "\"Good is thy riddle, Gestumblindi,",
          "and guessed it is:",
          "That is the game of hneftafl: weaponless, the figures slay each other for the sake of their king. The red ones are his followers.\""
        ],
        "placeholder": false
      },
      {
        "id": "39",
        "type": "prose",
        "number": "",
        "lines": [
          ""
        ],
        "placeholder": false
      },
      {
        "id": "40",
        "type": "stanza",
        "number": "20.",
        "lines": [
          "Gestumblindi said:",
          "\"Who be the playmates that pass over the lands,",
          "seeming fair to their father?",
          "A white shield they show in winter,",
          "and a swart one in summer.",
          "Aright guess now this riddle, Heithrek!\"",
          "Heithrek said:",
          "\"Good is thy riddle, Gestumblindi,",
          "and guessed it is:",
          "they are the ptarmigans. They are white in winter and black in summer.\""
        ],
        "placeholder": false
      },
      {
        "id": "41",
        "type": "prose",
        "number": "",
        "lines": [
          ""
        ],
        "placeholder": false
      },
      {
        "id": "42",
        "type": "stanza",
        "number": "21.",
        "lines": [
          "Gestumblindi said:",
          "\"Who be the sisters that sorrowing fare,",
          "seeming fair to their father?",
          "Many a man their might hath known",
          "and thus they live their lives.",
          "Aright guess now this riddle, Heithrek!\"",
          "Heithrek said:",
          "\"Good is thy riddle, Gestumblindi,",
          "and guessed it is:",
          "They are the billows. They are called the maids of Ægir.\""
        ],
        "placeholder": false
      },
      {
        "id": "43",
        "type": "prose",
        "number": "",
        "lines": [
          ""
        ],
        "placeholder": false
      },
      {
        "id": "44",
        "type": "stanza",
        "number": "22.",
        "lines": [
          "Gestumblindi said:",
          "\"Who be the maids that fare, many together,",
          "seeming fair to their father?",
          "Whitish hair have the white-hooded ones,",
          "and no man is with the maids.",
          "Aright guess now this riddle, Heithrek!\"",
          "Heithrek said:",
          "\"Good is thy riddle, Gestumblindi,",
          "and guessed it is:",
          "but these are the waves, as before.\""
        ],
        "placeholder": false
      },
      {
        "id": "45",
        "type": "prose",
        "number": "",
        "lines": [
          ""
        ],
        "placeholder": false
      },
      {
        "id": "46",
        "type": "stanza",
        "number": "23.",
        "lines": [
          "Gestumblindi said:",
          "\"Who be the widows that band all together,",
          "seeming fair to their father?",
          "They are seldom kind to sailor-folk,",
          "and are wide awake in the wind.",
          "Aright guess now this riddle, Heithrek!\"",
          "Heithrek said:",
          "\"Good is thy riddle, Gestumblindi,",
          "and guessed it is:",
          "they are Ægir’s widows. Thus are called the breakers.\""
        ],
        "placeholder": false
      },
      {
        "id": "47",
        "type": "prose",
        "number": "",
        "lines": [
          ""
        ],
        "placeholder": false
      },
      {
        "id": "48",
        "type": "stanza",
        "number": "24.",
        "lines": [
          "Gestumblindi said:",
          "\"Who be the women that wade in the surf",
          "and fare along the firths?",
          "A hard bed have the white-hooded ones,",
          "and quiet are they in calm.",
          "Aright guess now this riddle, Heithrek!\"",
          "Heithrek said:",
          "\"Good is thy riddle, Gestumblindi,",
          "and guessed it is:",
          "they are the billows—their beds are skerries and shingle, and they become somewhat sluggish in calm weather.\""
        ],
        "placeholder": false
      },
      {
        "id": "49",
        "type": "prose",
        "number": "",
        "lines": [
          ""
        ],
        "placeholder": false
      },
      {
        "id": "50",
        "type": "stanza",
        "number": "25.",
        "lines": [
          "Gestumblindi said:",
          "\"I saw traveling a soil’s-earth-dweller,",
          "a corpse sate on a corpse;",
          "one blind rode a blind thing to the billows-road,",
          "and no life was in the nag.",
          "Aright guess now this riddle, Heithrek!\"",
          "Heithrek said:",
          "\"Good is thy riddle, Gestumblindi,",
          "and guessed it is:",
          "you came to a river, and an ice-floe floated down it. On the floe lay a dead horse, and on the horse, a dead snake; so that one blind thing rode another blind thing.\""
        ],
        "placeholder": false
      },
      {
        "id": "51",
        "type": "prose",
        "number": "",
        "lines": [
          ""
        ],
        "placeholder": false
      },
      {
        "id": "52",
        "type": "stanza",
        "number": "26.",
        "lines": [
          "Gestumblindi said:",
          "\"What creature kills the cattle men have,",
          "and is iron-clad, without?",
          "Eight horns it has, but head it has none,",
          "and runs when run it may.",
          "Aright guess now this riddle, Heithrek!\"",
          "Heithrek said:",
          "\"Good is thy riddle, Gestumblindi,",
          "and guessed it is:",
          "that is the húnn on the checkerboard. It shares its name with the bear, and it runs as soon as it is overthrown.\""
        ],
        "placeholder": false
      },
      {
        "id": "53",
        "type": "prose",
        "number": "",
        "lines": [
          ""
        ],
        "placeholder": false
      },
      {
        "id": "54",
        "type": "stanza",
        "number": "27.",
        "lines": [
          "Gestumblindi said:",
          "\"What beast is it which brave men shelters?",
          "It has a bloody back and wards off blows,",
          "goes against spears, life-giving to some.",
          "Against lords left hand it lays its body.",
          "Aright guess now this riddle, Heithrek!\"",
          "Heithrek said:",
          "\"Good is thy riddle, Gestumblindi,",
          "and guessed it is:",
          "that is the shield. It often becomes bloody in battle, shielding those men who are handy with it.\""
        ],
        "placeholder": false
      },
      {
        "id": "55",
        "type": "prose",
        "number": "",
        "lines": [
          ""
        ],
        "placeholder": false
      },
      {
        "id": "56",
        "type": "stanza",
        "number": "28.",
        "lines": [
          "Gestumblindi said:",
          "\"Greatly had grown a goose with big neb,",
          "had brought timber together, for goslings eager.",
          "Gave shelter to her the sheaves bite-swords;",
          "but above it lay the drink’s dinful-rockcave,",
          "Aright guess now this riddle, Heithrek!\"",
          "Heithrek said:",
          "\"Good is thy riddle, Gestumblindi,",
          "and guessed it is:",
          "that is a duck which had built her nest between the jaws of an ox, with the skull roofing above it.\""
        ],
        "placeholder": false
      },
      {
        "id": "57",
        "type": "prose",
        "number": "",
        "lines": [
          ""
        ],
        "placeholder": false
      },
      {
        "id": "58",
        "type": "stanza",
        "number": "29.",
        "lines": [
          "Gestumblindi said:",
          "\"Four do hang and four do gang;",
          "two show the way, two ward off dogs;",
          "one drags after, most often dirty.",
          "Aright guess now this riddle, Heithrek!\"",
          "Heithrek said:",
          "\"Good is thy riddle, Gestumblindi,",
          "and guessed it is:",
          "that is a cow. She has four feet and four tits, two horns and two eyes, and her tail drags after her.\""
        ],
        "placeholder": false
      },
      {
        "id": "59",
        "type": "prose",
        "number": "",
        "lines": [
          ""
        ],
        "placeholder": false
      },
      {
        "id": "60",
        "type": "stanza",
        "number": "30.",
        "lines": [
          "Gestumblindi said:",
          "\"Who is the one that in the ashpit sleeps:",
          "and is only struck out of stone?",
          "Neither father nor mother has the greedy fiend",
          "there he wants to live his life.",
          "Aright guess now this riddle, Heithrek!\"",
          "Heithrek said:",
          "\"Good is thy riddle, Gestumblindi,",
          "and guessed it is:",
          "that is the fire hidden in the hearth—it is struck out of flint.\""
        ],
        "placeholder": false
      },
      {
        "id": "61",
        "type": "prose",
        "number": "",
        "lines": [
          ""
        ],
        "placeholder": false
      },
      {
        "id": "62",
        "type": "stanza",
        "number": "31.",
        "lines": [
          "Gestumblindi said:",
          "\"A stallion stood bestriding a mare;",
          "he put buttock neath belly and bobbed with his tail.",
          "Draw it out and in, work at it long!",
          "Aright guess now this riddle, Heithrek!\"",
          "Heithrek said:",
          "\"Good is thy riddle, Gestumblindi,",
          "and guessed it is:",
          "that horse is a piece of linen on the loom. His mare is the weaver’s reed, and up and down is the web to be shaken.\""
        ],
        "placeholder": false
      },
      {
        "id": "63",
        "type": "prose",
        "number": "",
        "lines": [
          ""
        ],
        "placeholder": false
      },
      {
        "id": "64",
        "type": "stanza",
        "number": "32.",
        "lines": [
          "Gestumblindi said:",
          "\"Who be the thanes to the thing who ride?",
          "Sixteen are in that set.",
          "Their liege-men send they over all the lands,",
          "to seek a place to settle.",
          "Aright guess now this riddle, Heithrek!\"",
          "Heithrek said:",
          "\"Good is thy riddle, Gestumblindi,",
          "and guessed it is:",
          "they are Itrek and Andath sitting on their checkerboard.\""
        ],
        "placeholder": false
      },
      {
        "id": "65",
        "type": "prose",
        "number": "",
        "lines": [
          ""
        ],
        "placeholder": false
      },
      {
        "id": "66",
        "type": "stanza",
        "number": "33.",
        "lines": [
          "Gestumblindi said:",
          "\"In the summer saw I, at sunset time,",
          "a merry band at festive board;",
          "the men did drink their mead in peace,",
          "the while the mead-keg muttering stood.",
          "Aright guess now this riddle, Heithrek!\"",
          "Heithrek said:",
          "\"Good is thy riddle, Gestumblindi,",
          "and guessed it is:",
          "that is a sow with her shoats. When the pigs suck her she grunts, while they keep quiet.\""
        ],
        "placeholder": false
      },
      {
        "id": "67",
        "type": "prose",
        "number": "",
        "lines": [
          ""
        ],
        "placeholder": false
      },
      {
        "id": "68",
        "type": "stanza",
        "number": "34.",
        "lines": [
          "Gestumblindi said:",
          "\"Maidens saw I which were much like dust;",
          "boulders served them as beds.",
          "Are they swart and sallow in sunny weather,",
          "but the fairer, the fainter the light.",
          "Aright guess now this riddle, Heithrek!\"",
          "Heithrek said:",
          "\"Good is thy riddle, Gestumblindi,",
          "and guessed it is:",
          "they are the gledes dying on the hearth.\""
        ],
        "placeholder": false
      },
      {
        "id": "69",
        "type": "prose",
        "number": "",
        "lines": [
          ""
        ],
        "placeholder": false
      },
      {
        "id": "70",
        "type": "stanza",
        "number": "35.",
        "lines": [
          "Gestumblindi said:",
          "\"On a sail I sate and saw dead men",
          "who a blood-vein bore to the bark of a tree.",
          "Aright guess now this riddle, Heithrek!\"",
          "Heithrek said:",
          "\"Good is thy riddle, Gestumblindi,",
          "and guessed it is:",
          "You sate on a wall and saw a falcon bear an eider duck to the cliff.\""
        ],
        "placeholder": false
      },
      {
        "id": "71",
        "type": "prose",
        "number": "",
        "lines": [
          ""
        ],
        "placeholder": false
      },
      {
        "id": "72",
        "type": "stanza",
        "number": "36.",
        "lines": [
          "Gestumblindi said:",
          "\"Who are the twain that on ten feet run?",
          "three eyes they have, but only one tail.",
          "Aright guess now this riddle, Heithrek!\"",
          "Heithrek said:",
          "\"Good is thy riddle, Gestumblindi,",
          "and guessed it is:",
          "that is Óthin riding on Sleipnir.\""
        ],
        "placeholder": false
      },
      {
        "id": "73",
        "type": "prose",
        "number": "",
        "lines": [
          ""
        ],
        "placeholder": false
      },
      {
        "id": "74",
        "type": "stanza",
        "number": "37.",
        "lines": [
          "Gestumblindi said:",
          "\"Guess one more riddle, since wiser thou seemest",
          "than any other wight:",
          "what said Óthin in Baldr’s ear",
          "before he was borne to the fire?\"",
          "Heithrek said:",
          "\"But wicked spells and wantonness",
          "I ween that it was:",
          "the words thou spakest no wight knoweth",
          "but thou, ill and unclean wight.\""
        ],
        "placeholder": false
      },
      {
        "id": "75",
        "type": "prose",
        "number": "",
        "lines": [
          ""
        ],
        "placeholder": false
      }
    ]
  }
}
